DarkThon/__init__.py
DarkThon-1.0.1.dist-info/METADATA
DarkThon-1.0.1.dist-info/WHEEL
DarkThon-1.0.1.dist-info/top_level.txt
DarkThon-1.0.1.dist-info/RECORD
